eyedlog/__init__.py
eyedlog/__version__.py
eyedlog/compress.py
eyedlog/logging.py
eyedlog-0.0.7.dist-info/LICENSE
eyedlog-0.0.7.dist-info/METADATA
eyedlog-0.0.7.dist-info/WHEEL
eyedlog-0.0.7.dist-info/top_level.txt
eyedlog-0.0.7.dist-info/RECORD
