Metadata-Version: 2.1
Name: eyedlog
Version: 0.0.7
Summary: Colored log
Home-page: https://gitee.com/ferras/eyedlog
Author: Ferras Meng
Author-email: 469611602@qq.com
License: MIT
Keywords: colored,readable,log
Platform: UNKNOWN
Classifier: Intended Audience :: Developers
Classifier: Topic :: Software Development :: Libraries :: Python Modules
Classifier: Programming Language :: Python :: 3.6
Classifier: Programming Language :: Python :: 3.7
Classifier: Programming Language :: Python :: 3.8
Classifier: Programming Language :: Python :: 3.9
Classifier: Programming Language :: Python :: 3.10
License-File: LICENSE
